LICENSE
README.md
setup.cfg
setup.py
django_fsm_log/__init__.py
django_fsm_log/admin.py
django_fsm_log/apps.py
django_fsm_log/backends.py
django_fsm_log/checks.py
django_fsm_log/conf.py
django_fsm_log/decorators.py
django_fsm_log/helpers.py
django_fsm_log/managers.py
django_fsm_log/models.py
django_fsm_log/migrations/0001_initial.py
django_fsm_log/migrations/0002_auto_20151207_1521.py
django_fsm_log/migrations/0003_statelog_description.py
django_fsm_log/migrations/0003_statelog_description_squashed_0005_description_null.py
django_fsm_log/migrations/0004_add_source_state.py
django_fsm_log/migrations/0005_description_null.py
django_fsm_log/migrations/0006_allow_non_numeric_ids.py
django_fsm_log/migrations/__init__.py
django_fsm_logger.egg-info/PKG-INFO
django_fsm_logger.egg-info/SOURCES.txt
django_fsm_logger.egg-info/dependency_links.txt
django_fsm_logger.egg-info/requires.txt
django_fsm_logger.egg-info/top_level.txt
tests/__init__.py
tests/admin.py
tests/conftest.py
tests/models.py
tests/settings.py
tests/test_admin.py
tests/test_manager.py
tests/test_model.py
tests/test_settings.py
tests/urls.py